objectdb/__init__.py
objectdb/api.py
objectdb/database.py
objectdb/foreign_key.py
objectdb/models.py
objectdb/py.typed
objectdb/scheduler.py
objectdb/backends/__init__.py
objectdb/backends/dictionary.py
objectdb/backends/mongodb.py
objectdb-0.25.0.dist-info/METADATA
objectdb-0.25.0.dist-info/WHEEL
objectdb-0.25.0.dist-info/licenses/LICENSE
objectdb-0.25.0.dist-info/RECORD
