Metadata-Version: 2.4
Name: objectdb
Version: 0.25.0
Author: Felix Trautwein <mail@felixtrautwein.de>
License-File: LICENSE
Requires-Dist: fastapi>=0.118.0
Requires-Dist: pydantic-core>=2.0
Requires-Dist: pydantic>=2.0
Requires-Dist: pymongo>=4.15.2
Requires-Dist: pytest-asyncio>=1.2.0
